winzig/__init__.py
winzig/commands/__init__.py
winzig/commands/crawl.py
winzig/commands/export.py
winzig/commands/search.py
winzig/commands/tui.py
winzig/config.py
winzig/console.py
winzig/crawler.py
winzig/database.py
winzig/main.py
winzig/management.py
winzig/models.py
winzig/search_engine.py
winzig/tf_idf.py
winzig/tui.py
winzig/tui.tcss
winzig/utils.py
winzig-0.3.0.dist-info/LICENSE
winzig-0.3.0.dist-info/METADATA
winzig-0.3.0.dist-info/WHEEL
winzig-0.3.0.dist-info/entry_points.txt
winzig-0.3.0.dist-info/RECORD
