Metadata-Version: 2.1
Name: winzig
Version: 0.3.0
Summary: A tiny search engine for personal use.
Home-page: https://github.com/dnlzrgz/winzig
License: MIT
Keywords: search,crawl,sqlite,async,feeds
Author: dnlzrgz
Author-email: 24715931+dnlzrgz@users.noreply.github.com
Requires-Python: >=3.12,<4.0
Classifier: License :: OSI Approved :: MIT License
Classifier: Programming Language :: Python :: 3
Classifier: Programming Language :: Python :: 3.12
Requires-Dist: aiohttp[speedups] (>=3.9.3,<4.0.0)
Requires-Dist: aiosqlite (>=0.20.0,<0.21.0)
Requires-Dist: click (>=8.1.7,<9.0.0)
Requires-Dist: emoji (>=2.10.1,<3.0.0)
Requires-Dist: feedparser (>=6.0.11,<7.0.0)
Requires-Dist: rich (>=13.7.1,<14.0.0)
Requires-Dist: selectolax (>=0.3.20,<0.4.0)
Requires-Dist: sqlalchemy[asyncio] (>=2.0.28,<3.0.0)
Requires-Dist: textual (>=0.52.1,<0.53.0)
Requires-Dist: tldextract (>=5.1.2,<6.0.0)
Project-URL: Repository, https://github.com/dnlzrgz/winzig
